{
  "type": "minecraft:crafting_shapeless",
  "category": "misc",
  "ingredients": [
    {
      "type": "neoforge:nbt",
      "Count": 1,
      "id": "veganoption:soap",
      "tag": {
        "Damage": 0
      }
    },
    {
      "item": "minecraft:sugar"
    },
    {
      "item": "minecraft:sugar"
    },
    {
      "item": "minecraft:sugar"
    },
    {
      "item": "minecraft:sugar"
    },
    {
      "item": "minecraft:water_bucket"
    }
  ],
  "result": {
    "item": "veganoption:soap_solution_bucket"
  }
}